{"lastUsed":1725188465365,"path":"D:\/codes","projectCount":3,"recentFiles":[{"path":"\/JavaHashMap\/src\/hasMapMethods","parentWorkspace":"D:\/codes","name":"JavaHashMap_clone.java","lastModified":1725014026476,"locationURI":"file:\/D:\/codes\/JavaHashMap\/src\/hasMapMethods\/JavaHashMap_clone.java"},{"path":"\/JavaHashMap\/src\/hashMap","parentWorkspace":"D:\/codes","name":"JavaHashMap.java","lastModified":1725003006411,"locationURI":"file:\/D:\/codes\/JavaHashMap\/src\/hashMap\/JavaHashMap.java"},{"path":"\/JavaList\/src\/programsOnList","parentWorkspace":"D:\/codes","name":"OnlyOddNumbers.java","lastModified":1725005299728,"locationURI":"file:\/D:\/codes\/JavaList\/src\/programsOnList\/OnlyOddNumbers.java"},{"path":"\/JavaHashMap\/src\/hasMapMethods","parentWorkspace":"D:\/codes","name":"JavaHashMap_containsKey.java","lastModified":1725013257140,"locationURI":"file:\/D:\/codes\/JavaHashMap\/src\/hasMapMethods\/JavaHashMap_containsKey.java"},{"path":"\/JavaHashMap\/src\/hasMapMethods","parentWorkspace":"D:\/codes","name":"JavaHashMap_compute.java","lastModified":1725013249041,"locationURI":"file:\/D:\/codes\/JavaHashMap\/src\/hasMapMethods\/JavaHashMap_compute.java"},{"path":"\/JavaArrays\/src\/sliceArray","parentWorkspace":"D:\/codes","name":"JavaSliceAnArray.java","lastModified":1724996555099,"locationURI":"file:\/D:\/codes\/JavaArrays\/src\/sliceArray\/JavaSliceAnArray.java"},{"path":"\/JavaHashMap\/src\/hasMapMethods","parentWorkspace":"D:\/codes","name":"JavaHashMap_containsValue.java","lastModified":1725005240168,"locationURI":"file:\/D:\/codes\/JavaHashMap\/src\/hasMapMethods\/JavaHashMap_containsValue.java"},{"path":"\/JavaHashMap\/src\/hasMapMethods","parentWorkspace":"D:\/codes","name":"JavaHashMap_clear.java","lastModified":1725014026226,"locationURI":"file:\/D:\/codes\/JavaHashMap\/src\/hasMapMethods\/JavaHashMap_clear.java"}]}